{
  "generated_at": "2026-05-03T11:34:54.895752+08:00",
  "total_titles_processed": 545,
  "failed_sources": [],
  "trends": [
    {
      "keyword_group": "社会新闻 泉州 福建",
      "match_count": 4,
      "titles": [
        {
          "title": "媒体：泉州一高校因学生走路看手机劝退学生还辞退4名教师？各方回应",
          "url": "https://m.thepaper.cn/newsDetail_forward_33092359",
          "source": "澎湃新闻",
          "ranks": [
            12,
            9
          ],
          "is_new": false,
          "appearance_count": 2,
          "time_info": "[00时54分 ~ 11时34分]"
        },
        {
          "title": "福州1-0战胜泉州",
          "url": "https://www.baidu.com/s?wd=%E7%A6%8F%E5%B7%9E1-0%E6%88%98%E8%83%9C%E6%B3%89%E5%B7%9E",
          "source": "百度热搜",
          "ranks": [
            9
          ],
          "is_new": false,
          "appearance_count": 1,
          "time_info": "00时54分"
        },
        {
          "title": "闽超福州1:0泉州",
          "url": "https://www.douyin.com/hot/2486970",
          "source": "抖音",
          "ranks": [
            19
          ],
          "is_new": false,
          "appearance_count": 1,
          "time_info": "00时54分"
        },
        {
          "title": "闽超泉州主场赵文卓再现“郑成功”",
          "url": "https://www.baidu.com/s?wd=%E9%97%BD%E8%B6%85%E6%B3%89%E5%B7%9E%E4%B8%BB%E5%9C%BA%E8%B5%B5%E6%96%87%E5%8D%93%E5%86%8D%E7%8E%B0%E2%80%9C%E9%83%91%E6%88%90%E5%8A%9F%E2%80%9D",
          "source": "百度热搜",
          "ranks": [
            28
          ],
          "is_new": false,
          "appearance_count": 1,
          "time_info": "00时54分"
        }
      ]
    },
    {
      "keyword_group": "美股",
      "match_count": 2,
      "titles": [
        {
          "title": "美股股指创新高，下跌个股却远超上涨？高盛：动量拥挤，逆转将引发剧烈回撤",
          "url": "https://wallstreetcn.com/articles/3771483",
          "source": "华尔街见闻",
          "ranks": [
            7
          ],
          "is_new": true,
          "appearance_count": 1,
          "time_info": "11时34分"
        },
        {
          "title": "美股收盘：三大内存股收创纪录 标普纳指连两日刷新高",
          "url": "https://www.cls.cn/detail/2362019",
          "source": "财联社热门",
          "ranks": [
            12
          ],
          "is_new": false,
          "appearance_count": 1,
          "time_info": "00时54分"
        }
      ]
    },
    {
      "keyword_group": "NBA 篮球",
      "match_count": 1,
      "titles": [
        {
          "title": "NBA再次上演黑七",
          "url": "https://search.bilibili.com/all?keyword=NBA%E5%86%8D%E6%AC%A1%E4%B8%8A%E6%BC%94%E9%BB%91%E4%B8%83",
          "source": "bilibili 热搜",
          "ranks": [
            1
          ],
          "is_new": true,
          "appearance_count": 1,
          "time_info": "11时34分"
        }
      ]
    }
  ],
  "report_image_url": "https://github.com/wjj628/TrendRadar/img/news.jpg"
}