{
  "generated_at": "2025-12-04T09:52:18.959489+08:00",
  "total_titles_processed": 480,
  "failed_sources": [],
  "trends": [
    {
      "keyword_group": "美股",
      "match_count": 6,
      "titles": [
        {
          "title": "美股涨，数字货币大体收复周一暴跌失地，离岸人民币迈向14个月高位，白银V形反转",
          "url": "https://wallstreetcn.com/articles/3760523",
          "source": "华尔街见闻",
          "ranks": [
            2
          ],
          "is_new": false,
          "appearance_count": 1,
          "time_info": "00时34分"
        },
        {
          "title": "美股机器人板块整体走强 据称美国政府已准备布局这一领域",
          "url": "https://www.cls.cn/detail/2218940",
          "source": "财联社热门",
          "ranks": [
            3
          ],
          "is_new": true,
          "appearance_count": 1,
          "time_info": "09时52分"
        },
        {
          "title": "小非农超预期降温，美股集体低开，美元短线跳水，伦铜涨破纪录，白银高位震荡，比特币短线V形反弹",
          "url": "https://wallstreetcn.com/articles/3760624",
          "source": "华尔街见闻",
          "ranks": [
            4
          ],
          "is_new": false,
          "appearance_count": 1,
          "time_info": "00时34分"
        },
        {
          "title": "美股收盘：三大指数艰难冲刺新高 有色、机器人板块走强",
          "url": "https://www.cls.cn/detail/2218975",
          "source": "财联社热门",
          "ranks": [
            5
          ],
          "is_new": true,
          "appearance_count": 1,
          "time_info": "09时52分"
        },
        {
          "title": "美国11月ADP就业减少3.2万 美股三大期指集体上涨 | 今夜看点",
          "url": "https://www.cls.cn/detail/2218814",
          "source": "财联社热门",
          "ranks": [
            13
          ],
          "is_new": true,
          "appearance_count": 1,
          "time_info": "09时52分"
        },
        {
          "title": "微软(MSFT.O)美股跌幅收窄，现跌1.5%。",
          "url": "https://flash.jin10.com/detail/20251203234502090800",
          "source": "金十数据",
          "ranks": [
            28
          ],
          "is_new": false,
          "appearance_count": 1,
          "time_info": "00时34分"
        }
      ]
    },
    {
      "keyword_group": "NBA 篮球",
      "match_count": 1,
      "titles": [
        {
          "title": "正直播NBA：开拓者vs骑士",
          "url": "https://www.baidu.com/s?wd=%E6%AD%A3%E7%9B%B4%E6%92%ADNBA%EF%BC%9A%E5%BC%80%E6%8B%93%E8%80%85vs%E9%AA%91%E5%A3%AB",
          "source": "百度热搜",
          "ranks": [
            30
          ],
          "is_new": true,
          "appearance_count": 1,
          "time_info": "09时52分"
        }
      ]
    }
  ],
  "report_image_url": "https://github.com/wjj628/TrendRadar/img/news.jpg"
}