{
  "generated_at": "2026-06-06T18:08:24.582670+08:00",
  "total_titles_processed": 750,
  "failed_sources": [],
  "trends": [
    {
      "keyword_group": "美股",
      "match_count": 8,
      "titles": [
        {
          "title": "非农大超预期，美股债“双杀”，纳指重挫超4%，芯片指数暴跌10%，贵金属、加密货币遭“血洗”",
          "url": "https://wallstreetcn.com/articles/3773946",
          "source": "华尔街见闻",
          "ranks": [
            1
          ],
          "is_new": false,
          "appearance_count": 3,
          "time_info": "[11时47分 ~ 18时08分]"
        },
        {
          "title": "美股收盘：强劲非农引发加息担忧 AI热潮降温纳指重挫逾4%",
          "url": "https://www.cls.cn/detail/2392497",
          "source": "财联社热门",
          "ranks": [
            1
          ],
          "is_new": false,
          "appearance_count": 3,
          "time_info": "[11时47分 ~ 18时08分]"
        },
        {
          "title": "美股三大指数集体收跌，纳指跌超 1100 点，美国非农数据大幅超预期，加息预期升温，哪些信息值得关注？",
          "url": "https://www.zhihu.com/question/2046360260902909588",
          "source": "知乎",
          "ranks": [
            5
          ],
          "is_new": false,
          "appearance_count": 3,
          "time_info": "[11时47分 ~ 18时08分]"
        },
        {
          "title": "反“金发姑娘”！今晚非农：好消息和坏消息，对美股而言都是坏消息",
          "url": "https://wallstreetcn.com/articles/3773949",
          "source": "华尔街见闻",
          "ranks": [
            6,
            3
          ],
          "is_new": false,
          "appearance_count": 3,
          "time_info": "[01时58分 ~ 11时48分]"
        },
        {
          "title": "特朗普称美股应随“绝佳”就业报告上涨，哈塞特表示定价年内加息是错误的",
          "url": "https://wallstreetcn.com/articles/3773991",
          "source": "华尔街见闻",
          "ranks": [
            10
          ],
          "is_new": false,
          "appearance_count": 2,
          "time_info": "[11时47分 ~ 11时48分]"
        },
        {
          "title": "美股三大指数齐跌 纳指跌逾千点",
          "url": "https://www.toutiao.com/trending/7647681791742214171/",
          "source": "今日头条",
          "ranks": [
            20
          ],
          "is_new": false,
          "appearance_count": 2,
          "time_info": "[11时47分 ~ 11时48分]"
        },
        {
          "title": "美股一夜蒸发超万亿美元市值",
          "url": "https://www.toutiao.com/trending/7648103085272731199/",
          "source": "今日头条",
          "ranks": [
            7
          ],
          "is_new": true,
          "appearance_count": 1,
          "time_info": "18时08分"
        },
        {
          "title": "开户就送“美股七姐妹”，部分港资券商抢开户，最后的窗口期真能安全吗？",
          "url": "https://www.cls.cn/detail/2392638",
          "source": "财联社热门",
          "ranks": [
            13
          ],
          "is_new": true,
          "appearance_count": 1,
          "time_info": "18时08分"
        }
      ]
    },
    {
      "keyword_group": "NBA 篮球",
      "match_count": 6,
      "titles": [
        {
          "title": "NBA总决赛马刺vs尼克斯",
          "url": "https://s.weibo.com/weibo?q=NBA%E6%80%BB%E5%86%B3%E8%B5%9B%E9%A9%AC%E5%88%BAvs%E5%B0%BC%E5%85%8B%E6%96%AF&t=31&band_rank=4&Refer=top",
          "source": "微博",
          "ranks": [
            4
          ],
          "is_new": false,
          "appearance_count": 2,
          "time_info": "[11时47分 ~ 11时48分]"
        },
        {
          "title": "2526 赛季 NBA 总决赛 G2 马刺 104-105 尼克斯，如何评价本场比赛？",
          "url": "https://www.zhihu.com/question/2046412720908637248",
          "source": "知乎",
          "ranks": [
            4
          ],
          "is_new": true,
          "appearance_count": 1,
          "time_info": "18时08分"
        },
        {
          "title": "NBA总决赛第2场：尼克斯1分险胜马刺",
          "url": "https://www.baidu.com/s?wd=NBA%E6%80%BB%E5%86%B3%E8%B5%9B%E7%AC%AC2%E5%9C%BA%EF%BC%9A%E5%B0%BC%E5%85%8B%E6%96%AF1%E5%88%86%E9%99%A9%E8%83%9C%E9%A9%AC%E5%88%BA",
          "source": "百度热搜",
          "ranks": [
            7
          ],
          "is_new": false,
          "appearance_count": 2,
          "time_info": "[11时47分 ~ 11时48分]"
        },
        {
          "title": "NBA",
          "url": "https://s.weibo.com/weibo?q=NBA&t=31&band_rank=10&Refer=top",
          "source": "微博",
          "ranks": [
            10
          ],
          "is_new": false,
          "appearance_count": 2,
          "time_info": "[11时47分 ~ 11时48分]"
        },
        {
          "title": "25-26 赛季 NBA 总决赛 G2 马刺 VS 尼克斯，如何评价本场比赛？",
          "url": "https://www.zhihu.com/question/2046412720908637248",
          "source": "知乎",
          "ranks": [
            18
          ],
          "is_new": false,
          "appearance_count": 2,
          "time_info": "[11时47分 ~ 11时48分]"
        },
        {
          "title": "21世纪NBA总决赛百大炸裂瞬间",
          "url": "https://search.bilibili.com/all?keyword=21%E4%B8%96%E7%BA%AANBA%E6%80%BB%E5%86%B3%E8%B5%9B%E7%99%BE%E5%A4%A7%E7%82%B8%E8%A3%82%E7%9E%AC%E9%97%B4",
          "source": "bilibili 热搜",
          "ranks": [
            19
          ],
          "is_new": false,
          "appearance_count": 1,
          "time_info": "01时58分"
        }
      ]
    },
    {
      "keyword_group": "美债",
      "match_count": 2,
      "titles": [
        {
          "title": "非农大超预期，美债收益率短线拉升，AI降温纳指开盘跌超1.2%，WTI原油跌1%，现货白银跌超2.5%",
          "url": "https://wallstreetcn.com/articles/3773946",
          "source": "华尔街见闻",
          "ranks": [
            5
          ],
          "is_new": false,
          "appearance_count": 1,
          "time_info": "01时58分"
        },
        {
          "title": "美国如何一次性解决 36 万亿美债问题？",
          "url": "https://www.zhihu.com/question/6607165102",
          "source": "知乎",
          "ranks": [
            9
          ],
          "is_new": false,
          "appearance_count": 1,
          "time_info": "01时58分"
        }
      ]
    },
    {
      "keyword_group": "美元",
      "match_count": 2,
      "titles": [
        {
          "title": "美国芯片股单日蒸发逾万亿美元市值，费城半导体指数创六年最大单日跌幅",
          "url": "https://wallstreetcn.com/articles/3773996",
          "source": "华尔街见闻",
          "ranks": [
            8,
            5
          ],
          "is_new": false,
          "appearance_count": 3,
          "time_info": "[11时47分 ~ 18时08分]"
        },
        {
          "title": "彭博美元指数涨0.5%，创最近两个月最大盘中涨幅。",
          "url": "https://wallstreetcn.com/livenews/3115251",
          "source": "华尔街见闻-快讯",
          "ranks": [
            29
          ],
          "is_new": false,
          "appearance_count": 1,
          "time_info": "01时58分"
        }
      ]
    },
    {
      "keyword_group": "金价",
      "match_count": 1,
      "titles": [
        {
          "title": "金价跌回2025年",
          "url": "https://s.weibo.com/weibo?q=%23%E9%87%91%E4%BB%B7%E8%B7%8C%E5%9B%9E2025%E5%B9%B4%23&t=31&band_rank=22&Refer=top",
          "source": "微博",
          "ranks": [
            22
          ],
          "is_new": true,
          "appearance_count": 1,
          "time_info": "18时08分"
        }
      ]
    }
  ],
  "report_image_url": "https://github.com/wjj628/TrendRadar/img/news.jpg"
}